Workbook

Sheet README
A1: Sales Performance Analysis - FY Oct 2025 to Sep 2026
A2: Synthetic dataset (300 transactions, 12 products, 4 regions) created for practice. Not real company data.
A4: Sheets
A5: Sales_Data - raw transactions. Revenue and Profit are formulas. AutoFilter is on: filter by Region, Product, Returned, etc.
A6: Top_Transactions - top 15 transactions sorted by Revenue (descending).
A7: High_Value - every transaction at or above the high-value threshold, sorted by Revenue (descending).
A8: Product_Summary - revenue, profit and margin per product via SUMIFS. Status flags are driven by the blue threshold cells.
A9: Underperformers - filtered view of products flagged 'Underperforming', sorted by revenue (ascending).
A11: Definitions and assumptions
A12: Revenue = Quantity x Unit Price x (1 - Discount %). Profit = Revenue - Quantity x Unit Cost.
A13: High-value transaction = Revenue >= $32,400 (approx. 90th percentile of this dataset; typed in as a fixed number).
A14: Underperforming product = revenue below the share of average product revenue set in Product_Summary!B3, OR profit margin below B4.
... A16: If you edit Sales_Data, re-sort manually (Data > Sort) or ask for a refresh.

Sheet Sales_Data
A1: Transaction ID | B1: Date | C1: Region | D1: Salesperson | E1: Customer | F1: Product | G1: Category | H1: Quantity | I1: Unit Price ($) | J1: Discount % | K1: Unit Cost ($) | L1: Revenue ($) | M1: Profit ($) | N1: Returned
A2: TXN-1001 | B2: 45932 | C2: East | D2: Marcus Hill | E2: Nova Pharma | F2: Analytics Platform | G2: Software | H2: 4 | I2: 8500 | J2: 0.05 | K2: 3200 | L2: =H2*I2*(1-J2) -> 32300 | M2: =L2-H2*K2 -> 19500 | N2: N
A3: TXN-1002 | B3: 45934 | C3: West | D3: Daniel Cho | E3: Meridian Auto | F3: Smart Display 55in | G3: Hardware | H3: 1 | I3: 1900 | J3: 0.3 | K3: 1650 | L3: =H3*I3*(1-J3) -> 1330 | M3: =L3-H3*K3 -> -320 | N3: N
A4: TXN-1003 | B4: 45938 | C4: West | D4: Daniel Cho | E4: Nova Pharma | F4: Analytics Platform | G4: Software | H4: 4 | I4: 8500 | J4: 0 | K4: 3200 | L4: =H4*I4*(1-J4) -> 34000 | M4: =L4-H4*K4 -> 21200 | N4: N
A5: TXN-1004 | B5: 45938 | C5: South | D5: Priya Nair | E5: Juniper Foods | F5: Wireless Router W2 | G5: Hardware | H5: 8 | I5: 320 | J5: 0.15 | K5: 240 | L5: =H5*I5*(1-J5) -> 2176 | M5: =L5-H5*K5 -> 256 | N5: N
A6: TXN-1005 | B6: 45942 | C6: East | D6: Grace Liu | E6: Lumen Telecom | F6: Business Laptop L5 | G6: Hardware | H6: 25 | I6: 1450 | J6: 0.05 | K6: 1050 | L6: =H6*I6*(1-J6) -> 34437.5 | M6: =L6-H6*K6 -> 8187.5 | N6: N
A7: TXN-1006 | B7: 45942 | C7: North | D7: Tom Becker | E7: Keystone Edu | F7: Analytics Platform | G7: Software | H7: 2 | I7: 8500 | J7: 0.2 | K7: 3200 | L7: =H7*I7*(1-J7) -> 13600 | M7: =L7-H7*K7 -> 7200 | N7: N
A8: TXN-1007 | B8: 45944 | C8: East | D8: Grace Liu | E8: Meridian Auto | F8: Business Laptop L5 | G8: Hardware | H8: 10 | I8: 1450 | J8: 0.1 | K8: 1050 | L8: =H8*I8*(1-J8) -> 13050 | M8: =L8-H8*K8 -> 2550 | N8: N
A9: TXN-1008 | B9: 45945 | C9: East | D9: Marcus Hill | E9: Orion Travel | F9: Business Laptop L5 | G9: Hardware | H9: 25 | I9: 1450 | J9: 0 | K9: 1050 | L9: =H9*I9*(1-J9) -> 36250 | M9: =L9-H9*K9 -> 10000 | N9: N
A10: TXN-1009 | B10: 45945 | C10: North | D10: Tom Becker | E10: Keystone Edu | F10: Wireless Router W2 | G10: Hardware | H10: 10 | I10: 320 | J10: 0.2 | K10: 240 | L10: =H10*I10*(1-J10) -> 2560 | M10: =L10-H10*K10 -> 160 | N10: N
A11: TXN-1010 | B11: 45946 | C11: South | D11: Priya Nair | E11: Apex Corp | F11: Wireless Router W2 | G11: Hardware | H11: 15 | I11: 320 | J11: 0.05 | K11: 240 | L11: =H11*I11*(1-J11) -> 4560 | M11: =L11-H11*K11 -> 960 | N11: N
A12: TXN-1011 | B12: 45947 | C12: West | D12: Sofia Rossi | E12: Delta Retail | F12: Wireless Router W2 | G12: Hardware | H12: 25 | I12: 320 | J12: 0 | K12: 240 | L12: =H12*I12*(1-J12) -> 8000 | M12: =L12-H12*K12 -> 2000 | N12: Y
A13: TXN-1012 | B13: 45950 | C13: East | D13: Marcus Hill | E13: Fusion Media | F13: Analytics Platform | G13: Software | H13: 3 | I13: 8500 | J13: 0 | K13: 3200 | L13: =H13*I13*(1-J13) -> 25500 | M13: =L13-H13*K13 -> 15900 | N13: N
... A301: TXN-1300 | B301: 46295 | C301: South | D301: Luis Ortega | E301: Meridian Auto | F301: Business Laptop L5 | G301: Hardware | H301: 8 | I301: 1450 | J301: 0.2 | K301: 1050 | L301: =H301*I301*(1-J301) -> 9280 | M301: =L301-H301*K301 -> 880 | N301: N

Sheet Product_Summary
A1: Product Performance Summary
A3: Underperformance: revenue below this % of average product revenue | B3: 0.6 | C3: Edit the yellow cells to change what counts as underperforming.
A4: Underperformance: profit margin below | B4: 0.15
A6: Product | B6: Category | C6: Transactions | D6: Units Sold | E6: Revenue ($) | F6: Profit ($) | G6: Margin % | H6: Return Rate | I6: Revenue vs Avg | J6: Status
A7: Analytics Platform | B7: Software | C7: =COUNTIFS(Sales_Data!$F$2:$F$301,A7) -> 29 | D7: =SUMIFS(Sales_Data!$H$2:$H$301,Sales_Data!$F$2:$F$301,A7) -> 76 | E7: =SUMIFS(Sales_Data!$L$2:$L$301,Sales_Data!$F$2:$F$301,A7) -> 586925 | F7: =SUMIFS(Sales_Data!$M$2:$M$301,Sales_Data!$F$2:$F$301,A7) -> 343725 | G7: =IF(E7=0,0,F7/E7) -> 0.58563701 | H7: =IF(C7=0,0,COUNTIFS(Sales_Data!$F$2:$F$301,A7,Sales_Data!$N$2:$N$301,"Y")/C7) -> 0 | I7: =E7/AVERAGE($E$7:$E$18)-1 -> 0.6417781 | J7: =IF(OR(E7<$B$3*AVERAGE($E$7:$E$18),G7<$B$4),"Underperforming","OK") -> OK
A8: Basic Training Kit | B8: Services | C8: =COUNTIFS(Sales_Data!$F$2:$F$301,A8) -> 5 | D8: =SUMIFS(Sales_Data!$H$2:$H$301,Sales_Data!$F$2:$F$301,A8) -> 61 | E8: =SUMIFS(Sales_Data!$L$2:$L$301,Sales_Data!$F$2:$F$301,A8) -> 26970 | F8: =SUMIFS(Sales_Data!$M$2:$M$301,Sales_Data!$F$2:$F$301,A8) -> -4750 | G8: =IF(E8=0,0,F8/E8) -> -0.17612162 | H8: =IF(C8=0,0,COUNTIFS(Sales_Data!$F$2:$F$301,A8,Sales_Data!$N$2:$N$301,"Y")/C8) -> 0 | I8: =E8/AVERAGE($E$7:$E$18)-1 -> -0.92455807 | J8: =IF(OR(E8<$B$3*AVERAGE($E$7:$E$18),G8<$B$4),"Underperforming","OK") -> Underperforming
A9: Business Laptop L5 | B9: Hardware | C9: =COUNTIFS(Sales_Data!$F$2:$F$301,A9) -> 60 | D9: =SUMIFS(Sales_Data!$H$2:$H$301,Sales_Data!$F$2:$F$301,A9) -> 638 | E9: =SUMIFS(Sales_Data!$L$2:$L$301,Sales_Data!$F$2:$F$301,A9) -> 849192.5 | F9: =SUMIFS(Sales_Data!$M$2:$M$301,Sales_Data!$F$2:$F$301,A9) -> 179292.5 | G9: =IF(E9=0,0,F9/E9) -> 0.21113293 | H9: =IF(C9=0,0,COUNTIFS(Sales_Data!$F$2:$F$301,A9,Sales_Data!$N$2:$N$301,"Y")/C9) -> 0.016666667 | I9: =E9/AVERAGE($E$7:$E$18)-1 -> 1.3754068 | J9: =IF(OR(E9<$B$3*AVERAGE($E$7:$E$18),G9<$B$4),"Underperforming","OK") -> OK
A10: Cloud Backup Pro | B10: Software | C10: =COUNTIFS(Sales_Data!$F$2:$F$301,A10) -> 37 | D10: =SUMIFS(Sales_Data!$H$2:$H$301,Sales_Data!$F$2:$F$301,A10) -> 162 | E10: =SUMIFS(Sales_Data!$L$2:$L$301,Sales_Data!$F$2:$F$301,A10) -> 355560 | F10: =SUMIFS(Sales_Data!$M$2:$M$301,Sales_Data!$F$2:$F$301,A10) -> 209760 | G10: =IF(E10=0,0,F10/E10) -> 0.58994263 | H10: =IF(C10=0,0,COUNTIFS(Sales_Data!$F$2:$F$301,A10,Sales_Data!$N$2:$N$301,"Y")/C10) -> 0.027027027 | I10: =E10/AVERAGE($E$7:$E$18)-1 -> -0.0054084899 | J10: =IF(OR(E10<$B$3*AVERAGE($E$7:$E$18),G10<$B$4),"Underperforming","OK") -> OK
A11: Cybersecurity Shield | B11: Software | C11: =COUNTIFS(Sales_Data!$F$2:$F$301,A11) -> 25 | D11: =SUMIFS(Sales_Data!$H$2:$H$301,Sales_Data!$F$2:$F$301,A11) -> 69 | E11: =SUMIFS(Sales_Data!$L$2:$L$301,Sales_Data!$F$2:$F$301,A11) -> 387500 | F11: =SUMIFS(Sales_Data!$M$2:$M$301,Sales_Data!$F$2:$F$301,A11) -> 208100 | G11: =IF(E11=0,0,F11/E11) -> 0.53703226 | H11: =IF(C11=0,0,COUNTIFS(Sales_Data!$F$2:$F$301,A11,Sales_Data!$N$2:$N$301,"Y")/C11) -> 0.04 | I11: =E11/AVERAGE($E$7:$E$18)-1 -> 0.083935792 | J11: =IF(OR(E11<$B$3*AVERAGE($E$7:$E$18),G11<$B$4),"Underperforming","OK") -> OK
A12: Enterprise CRM Suite | B12: Software | C12: =COUNTIFS(Sales_Data!$F$2:$F$301,A12) -> 14 | D12: =SUMIFS(Sales_Data!$H$2:$H$301,Sales_Data!$F$2:$F$301,A12) -> 43 | E12: =SUMIFS(Sales_Data!$L$2:$L$301,Sales_Data!$F$2:$F$301,A12) -> 465000 | F12: =SUMIFS(Sales_Data!$M$2:$M$301,Sales_Data!$F$2:$F$301,A12) -> 250000 | G12: =IF(E12=0,0,F12/E12) -> 0.53763441 | H12: =IF(C12=0,0,COUNTIFS(Sales_Data!$F$2:$F$301,A12,Sales_Data!$N$2:$N$301,"Y")/C12) -> 0.071428571 | I12: =E12/AVERAGE($E$7:$E$18)-1 -> 0.30072295 | J12: =IF(OR(E12<$B$3*AVERAGE($E$7:$E$18),G12<$B$4),"Underperforming","OK") -> OK
A13: Legacy Fax Gateway | B13: Hardware | C13: =COUNTIFS(Sales_Data!$F$2:$F$301,A13) -> 3 | D13: =SUMIFS(Sales_Data!$H$2:$H$301,Sales_Data!$F$2:$F$301,A13) -> 22 | E13: =SUMIFS(Sales_Data!$L$2:$L$301,Sales_Data!$F$2:$F$301,A13) -> 7942.5 | F13: =SUMIFS(Sales_Data!$M$2:$M$301,Sales_Data!$F$2:$F$301,A13) -> -1077.5 | G13: =IF(E13=0,0,F13/E13) -> -0.13566257 | H13: =IF(C13=0,0,COUNTIFS(Sales_Data!$F$2:$F$301,A13,Sales_Data!$N$2:$N$301,"Y")/C13) -> 0 | I13: =E13/AVERAGE($E$7:$E$18)-1 -> -0.97778281 | J13: =IF(OR(E13<$B$3*AVERAGE($E$7:$E$18),G13<$B$4),"Underperforming","OK") -> Underperforming
A14: Onboarding Package | B14: Services | C14: =COUNTIFS(Sales_Data!$F$2:$F$301,A14) -> 24 | D14: =SUMIFS(Sales_Data!$H$2:$H$301,Sales_Data!$F$2:$F$301,A14) -> 318 | E14: =SUMIFS(Sales_Data!$L$2:$L$301,Sales_Data!$F$2:$F$301,A14) -> 532530 | F14: =SUMIFS(Sales_Data!$M$2:$M$301,Sales_Data!$F$2:$F$301,A14) -> 214530 | G14: =IF(E14=0,0,F14/E14) -> 0.40285054 | H14: =IF(C14=0,0,COUNTIFS(Sales_Data!$F$2:$F$301,A14,Sales_Data!$N$2:$N$301,"Y")/C14) -> 0.041666667 | I14: =E14/AVERAGE($E$7:$E$18)-1 -> 0.48962149 | J14: =IF(OR(E14<$B$3*AVERAGE($E$7:$E$18),G14<$B$4),"Underperforming","OK") -> OK
A15: Premium Support Plan | B15: Services | C15: =COUNTIFS(Sales_Data!$F$2:$F$301,A15) -> 16 | D15: =SUMIFS(Sales_Data!$H$2:$H$301,Sales_Data!$F$2:$F$301,A15) -> 83 | E15: =SUMIFS(Sales_Data!$L$2:$L$301,Sales_Data!$F$2:$F$301,A15) -> 268275 | F15: =SUMIFS(Sales_Data!$M$2:$M$301,Sales_Data!$F$2:$F$301,A15) -> 152075 | G15: =IF(E15=0,0,F15/E15) -> 0.56686236 | H15: =IF(C15=0,0,COUNTIFS(Sales_Data!$F$2:$F$301,A15,Sales_Data!$N$2:$N$301,"Y")/C15) -> 0.125 | I15: =E15/AVERAGE($E$7:$E$18)-1 -> -0.24956678 | J15: =IF(OR(E15<$B$3*AVERAGE($E$7:$E$18),G15<$B$4),"Underperforming","OK") -> OK
A16: Server Rack X900 | B16: Hardware | C16: =COUNTIFS(Sales_Data!$F$2:$F$301,A16) -> 21 | D16: =SUMIFS(Sales_Data!$H$2:$H$301,Sales_Data!$F$2:$F$301,A16) -> 62 | E16: =SUMIFS(Sales_Data!$L$2:$L$301,Sales_Data!$F$2:$F$301,A16) -> 570360 | F16: =SUMIFS(Sales_Data!$M$2:$M$301,Sales_Data!$F$2:$F$301,A16) -> 123960 | G16: =IF(E16=0,0,F16/E16) -> 0.21733642 | H16: =IF(C16=0,0,COUNTIFS(Sales_Data!$F$2:$F$301,A16,Sales_Data!$N$2:$N$301,"Y")/C16) -> 0.095238095 | I16: =E16/AVERAGE($E$7:$E$18)-1 -> 0.5954416 | J16: =IF(OR(E16<$B$3*AVERAGE($E$7:$E$18),G16<$B$4),"Underperforming","OK") -> OK
A17: Smart Display 55in | B17: Hardware | C17: =COUNTIFS(Sales_Data!$F$2:$F$301,A17) -> 5 | D17: =SUMIFS(Sales_Data!$H$2:$H$301,Sales_Data!$F$2:$F$301,A17) -> 24 | E17: =SUMIFS(Sales_Data!$L$2:$L$301,Sales_Data!$F$2:$F$301,A17) -> 33155 | F17: =SUMIFS(Sales_Data!$M$2:$M$301,Sales_Data!$F$2:$F$301,A17) -> -6445 | G17: =IF(E17=0,0,F17/E17) -> -0.19438999 | H17: =IF(C17=0,0,COUNTIFS(Sales_Data!$F$2:$F$301,A17,Sales_Data!$N$2:$N$301,"Y")/C17) -> 0 | I17: =E17/AVERAGE($E$7:$E$18)-1 -> -0.90725706 | J17: =IF(OR(E17<$B$3*AVERAGE($E$7:$E$18),G17<$B$4),"Underperforming","OK") -> Underperforming
A18: Wireless Router W2 | B18: Hardware | C18: =COUNTIFS(Sales_Data!$F$2:$F$301,A18) -> 61 | D18: =SUMIFS(Sales_Data!$H$2:$H$301,Sales_Data!$F$2:$F$301,A18) -> 706 | E18: =SUMIFS(Sales_Data!$L$2:$L$301,Sales_Data!$F$2:$F$301,A18) -> 206512 | F18: =SUMIFS(Sales_Data!$M$2:$M$301,Sales_Data!$F$2:$F$301,A18) -> 37072 | G18: =IF(E18=0,0,F18/E18) -> 0.17951499 | H18: =IF(C18=0,0,COUNTIFS(Sales_Data!$F$2:$F$301,A18,Sales_Data!$N$2:$N$301,"Y")/C18) -> 0.016393443 | I18: =E18/AVERAGE($E$7:$E$18)-1 -> -0.42233355 | J18: =IF(OR(E18<$B$3*AVERAGE($E$7:$E$18),G18<$B$4),"Underperforming","OK") -> Underperforming
A19: Total | C19: =SUM(C7:C18) -> 300 | D19: =SUM(D7:D18) -> 2264 | E19: =SUM(E7:E18) -> 4289922 | F19: =SUM(F7:F18) -> 1706242 | G19: =F19/E19 -> 0.39773264

Sheet Top_Transactions
A1: Top 15 Transactions by Revenue
A3: Rank | B3: Transaction ID | C3: Date | D3: Region | E3: Salesperson | F3: Customer | G3: Product | H3: Quantity | I3: Discount % | J3: Revenue ($) | K3: Profit ($)
A4: 1 | B4: TXN-1156 | C4: =INDEX(Sales_Data!$B$2:$B$301,MATCH($B4,Sales_Data!$A$2:$A$301,0)) -> 46117 | D4: =INDEX(Sales_Data!$C$2:$C$301,MATCH($B4,Sales_Data!$A$2:$A$301,0)) -> South | E4: =INDEX(Sales_Data!$D$2:$D$301,MATCH($B4,Sales_Data!$A$2:$A$301,0)) -> Priya Nair | F4: =INDEX(Sales_Data!$E$2:$E$301,MATCH($B4,Sales_Data!$A$2:$A$301,0)) -> Juniper Foods | G4: =INDEX(Sales_Data!$F$2:$F$301,MATCH($B4,Sales_Data!$A$2:$A$301,0)) -> Enterprise CRM Suite | H4: =INDEX(Sales_Data!$H$2:$H$301,MATCH($B4,Sales_Data!$A$2:$A$301,0)) -> 4 | I4: =INDEX(Sales_Data!$J$2:$J$301,MATCH($B4,Sales_Data!$A$2:$A$301,0)) -> 0 | J4: =INDEX(Sales_Data!$L$2:$L$301,MATCH($B4,Sales_Data!$A$2:$A$301,0)) -> 48000 | K4: =INDEX(Sales_Data!$M$2:$M$301,MATCH($B4,Sales_Data!$A$2:$A$301,0)) -> 28000
A5: 2 | B5: TXN-1227 | C5: =INDEX(Sales_Data!$B$2:$B$301,MATCH($B5,Sales_Data!$A$2:$A$301,0)) -> 46191 | D5: =INDEX(Sales_Data!$C$2:$C$301,MATCH($B5,Sales_Data!$A$2:$A$301,0)) -> North | E5: =INDEX(Sales_Data!$D$2:$D$301,MATCH($B5,Sales_Data!$A$2:$A$301,0)) -> Aisha Khan | F5: =INDEX(Sales_Data!$E$2:$E$301,MATCH($B5,Sales_Data!$A$2:$A$301,0)) -> BlueWave Ltd | G5: =INDEX(Sales_Data!$F$2:$F$301,MATCH($B5,Sales_Data!$A$2:$A$301,0)) -> Onboarding Package | H5: =INDEX(Sales_Data!$H$2:$H$301,MATCH($B5,Sales_Data!$A$2:$A$301,0)) -> 25 | I5: =INDEX(Sales_Data!$J$2:$J$301,MATCH($B5,Sales_Data!$A$2:$A$301,0)) -> 0 | J5: =INDEX(Sales_Data!$L$2:$L$301,MATCH($B5,Sales_Data!$A$2:$A$301,0)) -> 45000 | K5: =INDEX(Sales_Data!$M$2:$M$301,MATCH($B5,Sales_Data!$A$2:$A$301,0)) -> 20000
A6: 3 | B6: TXN-1204 | C6: =INDEX(Sales_Data!$B$2:$B$301,MATCH($B6,Sales_Data!$A$2:$A$301,0)) -> 46164 | D6: =INDEX(Sales_Data!$C$2:$C$301,MATCH($B6,Sales_Data!$A$2:$A$301,0)) -> North | E6: =INDEX(Sales_Data!$D$2:$D$301,MATCH($B6,Sales_Data!$A$2:$A$301,0)) -> Aisha Khan | F6: =INDEX(Sales_Data!$E$2:$E$301,MATCH($B6,Sales_Data!$A$2:$A$301,0)) -> Lumen Telecom | G6: =INDEX(Sales_Data!$F$2:$F$301,MATCH($B6,Sales_Data!$A$2:$A$301,0)) -> Enterprise CRM Suite | H6: =INDEX(Sales_Data!$H$2:$H$301,MATCH($B6,Sales_Data!$A$2:$A$301,0)) -> 4 | I6: =INDEX(Sales_Data!$J$2:$J$301,MATCH($B6,Sales_Data!$A$2:$A$301,0)) -> 0.1 | J6: =INDEX(Sales_Data!$L$2:$L$301,MATCH($B6,Sales_Data!$A$2:$A$301,0)) -> 43200 | K6: =INDEX(Sales_Data!$M$2:$M$301,MATCH($B6,Sales_Data!$A$2:$A$301,0)) -> 23200
A7: 4 | B7: TXN-1119 | C7: =INDEX(Sales_Data!$B$2:$B$301,MATCH($B7,Sales_Data!$A$2:$A$301,0)) -> 46077 | D7: =INDEX(Sales_Data!$C$2:$C$301,MATCH($B7,Sales_Data!$A$2:$A$301,0)) -> West | E7: =INDEX(Sales_Data!$D$2:$D$301,MATCH($B7,Sales_Data!$A$2:$A$301,0)) -> Sofia Rossi | F7: =INDEX(Sales_Data!$E$2:$E$301,MATCH($B7,Sales_Data!$A$2:$A$301,0)) -> Granite Bank | G7: =INDEX(Sales_Data!$F$2:$F$301,MATCH($B7,Sales_Data!$A$2:$A$301,0)) -> Enterprise CRM Suite | H7: =INDEX(Sales_Data!$H$2:$H$301,MATCH($B7,Sales_Data!$A$2:$A$301,0)) -> 4 | I7: =INDEX(Sales_Data!$J$2:$J$301,MATCH($B7,Sales_Data!$A$2:$A$301,0)) -> 0.1 | J7: =INDEX(Sales_Data!$L$2:$L$301,MATCH($B7,Sales_Data!$A$2:$A$301,0)) -> 43200 | K7: =INDEX(Sales_Data!$M$2:$M$301,MATCH($B7,Sales_Data!$A$2:$A$301,0)) -> 23200
A8: 5 | B8: TXN-1107 | C8: =INDEX(Sales_Data!$B$2:$B$301,MATCH($B8,Sales_Data!$A$2:$A$301,0)) -> 46059 | D8: =INDEX(Sales_Data!$C$2:$C$301,MATCH($B8,Sales_Data!$A$2:$A$301,0)) -> North | E8: =INDEX(Sales_Data!$D$2:$D$301,MATCH($B8,Sales_Data!$A$2:$A$301,0)) -> Tom Becker | F8: =INDEX(Sales_Data!$E$2:$E$301,MATCH($B8,Sales_Data!$A$2:$A$301,0)) -> Cobalt Systems | G8: =INDEX(Sales_Data!$F$2:$F$301,MATCH($B8,Sales_Data!$A$2:$A$301,0)) -> Onboarding Package | H8: =INDEX(Sales_Data!$H$2:$H$301,MATCH($B8,Sales_Data!$A$2:$A$301,0)) -> 25 | I8: =INDEX(Sales_Data!$J$2:$J$301,MATCH($B8,Sales_Data!$A$2:$A$301,0)) -> 0.05 | J8: =INDEX(Sales_Data!$L$2:$L$301,MATCH($B8,Sales_Data!$A$2:$A$301,0)) -> 42750 | K8: =INDEX(Sales_Data!$M$2:$M$301,MATCH($B8,Sales_Data!$A$2:$A$301,0)) -> 17750
A9: 6 | B9: TXN-1081 | C9: =INDEX(Sales_Data!$B$2:$B$301,MATCH($B9,Sales_Data!$A$2:$A$301,0)) -> 46029 | D9: =INDEX(Sales_Data!$C$2:$C$301,MATCH($B9,Sales_Data!$A$2:$A$301,0)) -> East | E9: =INDEX(Sales_Data!$D$2:$D$301,MATCH($B9,Sales_Data!$A$2:$A$301,0)) -> Marcus Hill | F9: =INDEX(Sales_Data!$E$2:$E$301,MATCH($B9,Sales_Data!$A$2:$A$301,0)) -> Cobalt Systems | G9: =INDEX(Sales_Data!$F$2:$F$301,MATCH($B9,Sales_Data!$A$2:$A$301,0)) -> Onboarding Package | H9: =INDEX(Sales_Data!$H$2:$H$301,MATCH($B9,Sales_Data!$A$2:$A$301,0)) -> 25 | I9: =INDEX(Sales_Data!$J$2:$J$301,MATCH($B9,Sales_Data!$A$2:$A$301,0)) -> 0.05 | J9: =INDEX(Sales_Data!$L$2:$L$301,MATCH($B9,Sales_Data!$A$2:$A$301,0)) -> 42750 | K9: =INDEX(Sales_Data!$M$2:$M$301,MATCH($B9,Sales_Data!$A$2:$A$301,0)) -> 17750
A10: 7 | B10: TXN-1124 | C10: =INDEX(Sales_Data!$B$2:$B$301,MATCH($B10,Sales_Data!$A$2:$A$301,0)) -> 46080 | D10: =INDEX(Sales_Data!$C$2:$C$301,MATCH($B10,Sales_Data!$A$2:$A$301,0)) -> West | E10: =INDEX(Sales_Data!$D$2:$D$301,MATCH($B10,Sales_Data!$A$2:$A$301,0)) -> Daniel Cho | F10: =INDEX(Sales_Data!$E$2:$E$301,MATCH($B10,Sales_Data!$A$2:$A$301,0)) -> Lumen Telecom | G10: =INDEX(Sales_Data!$F$2:$F$301,MATCH($B10,Sales_Data!$A$2:$A$301,0)) -> Enterprise CRM Suite | H10: =INDEX(Sales_Data!$H$2:$H$301,MATCH($B10,Sales_Data!$A$2:$A$301,0)) -> 4 | I10: =INDEX(Sales_Data!$J$2:$J$301,MATCH($B10,Sales_Data!$A$2:$A$301,0)) -> 0.15 | J10: =INDEX(Sales_Data!$L$2:$L$301,MATCH($B10,Sales_Data!$A$2:$A$301,0)) -> 40800 | K10: =INDEX(Sales_Data!$M$2:$M$301,MATCH($B10,Sales_Data!$A$2:$A$301,0)) -> 20800
A11: 8 | B11: TXN-1222 | C11: =INDEX(Sales_Data!$B$2:$B$301,MATCH($B11,Sales_Data!$A$2:$A$301,0)) -> 46186 | D11: =INDEX(Sales_Data!$C$2:$C$301,MATCH($B11,Sales_Data!$A$2:$A$301,0)) -> North | E11: =INDEX(Sales_Data!$D$2:$D$301,MATCH($B11,Sales_Data!$A$2:$A$301,0)) -> Aisha Khan | F11: =INDEX(Sales_Data!$E$2:$E$301,MATCH($B11,Sales_Data!$A$2:$A$301,0)) -> Keystone Edu | G11: =INDEX(Sales_Data!$F$2:$F$301,MATCH($B11,Sales_Data!$A$2:$A$301,0)) -> Server Rack X900 | H11: =INDEX(Sales_Data!$H$2:$H$301,MATCH($B11,Sales_Data!$A$2:$A$301,0)) -> 4 | I11: =INDEX(Sales_Data!$J$2:$J$301,MATCH($B11,Sales_Data!$A$2:$A$301,0)) -> 0 | J11: =INDEX(Sales_Data!$L$2:$L$301,MATCH($B11,Sales_Data!$A$2:$A$301,0)) -> 39200 | K11: =INDEX(Sales_Data!$M$2:$M$301,MATCH($B11,Sales_Data!$A$2:$A$301,0)) -> 10400
A12: 9 | B12: TXN-1214 | C12: =INDEX(Sales_Data!$B$2:$B$301,MATCH($B12,Sales_Data!$A$2:$A$301,0)) -> 46173 | D12: =INDEX(Sales_Data!$C$2:$C$301,MATCH($B12,Sales_Data!$A$2:$A$301,0)) -> East | E12: =INDEX(Sales_Data!$D$2:$D$301,MATCH($B12,Sales_Data!$A$2:$A$301,0)) -> Marcus Hill | F12: =INDEX(Sales_Data!$E$2:$E$301,MATCH($B12,Sales_Data!$A$2:$A$301,0)) -> Granite Bank | G12: =INDEX(Sales_Data!$F$2:$F$301,MATCH($B12,Sales_Data!$A$2:$A$301,0)) -> Server Rack X900 | H12: =INDEX(Sales_Data!$H$2:$H$301,MATCH($B12,Sales_Data!$A$2:$A$301,0)) -> 4 | I12: =INDEX(Sales_Data!$J$2:$J$301,MATCH($B12,Sales_Data!$A$2:$A$301,0)) -> 0 | J12: =INDEX(Sales_Data!$L$2:$L$301,MATCH($B12,Sales_Data!$A$2:$A$301,0)) -> 39200 | K12: =INDEX(Sales_Data!$M$2:$M$301,MATCH($B12,Sales_Data!$A$2:$A$301,0)) -> 10400
A13: 10 | B13: TXN-1019 | C13: =INDEX(Sales_Data!$B$2:$B$301,MATCH($B13,Sales_Data!$A$2:$A$301,0)) -> 45961 | D13: =INDEX(Sales_Data!$C$2:$C$301,MATCH($B13,Sales_Data!$A$2:$A$301,0)) -> West | E13: =INDEX(Sales_Data!$D$2:$D$301,MATCH($B13,Sales_Data!$A$2:$A$301,0)) -> Sofia Rossi | F13: =INDEX(Sales_Data!$E$2:$E$301,MATCH($B13,Sales_Data!$A$2:$A$301,0)) -> Granite Bank | G13: =INDEX(Sales_Data!$F$2:$F$301,MATCH($B13,Sales_Data!$A$2:$A$301,0)) -> Server Rack X900 | H13: =INDEX(Sales_Data!$H$2:$H$301,MATCH($B13,Sales_Data!$A$2:$A$301,0)) -> 4 | I13: =INDEX(Sales_Data!$J$2:$J$301,MATCH($B13,Sales_Data!$A$2:$A$301,0)) -> 0 | J13: =INDEX(Sales_Data!$L$2:$L$301,MATCH($B13,Sales_Data!$A$2:$A$301,0)) -> 39200 | K13: =INDEX(Sales_Data!$M$2:$M$301,MATCH($B13,Sales_Data!$A$2:$A$301,0)) -> 10400
A14: 11 | B14: TXN-1229 | C14: =INDEX(Sales_Data!$B$2:$B$301,MATCH($B14,Sales_Data!$A$2:$A$301,0)) -> 46193 | D14: =INDEX(Sales_Data!$C$2:$C$301,MATCH($B14,Sales_Data!$A$2:$A$301,0)) -> East | E14: =INDEX(Sales_Data!$D$2:$D$301,MATCH($B14,Sales_Data!$A$2:$A$301,0)) -> Marcus Hill | F14: =INDEX(Sales_Data!$E$2:$E$301,MATCH($B14,Sales_Data!$A$2:$A$301,0)) -> Ionic Energy | G14: =INDEX(Sales_Data!$F$2:$F$301,MATCH($B14,Sales_Data!$A$2:$A$301,0)) -> Enterprise CRM Suite | H14: =INDEX(Sales_Data!$H$2:$H$301,MATCH($B14,Sales_Data!$A$2:$A$301,0)) -> 4 | I14: =INDEX(Sales_Data!$J$2:$J$301,MATCH($B14,Sales_Data!$A$2:$A$301,0)) -> 0.2 | J14: =INDEX(Sales_Data!$L$2:$L$301,MATCH($B14,Sales_Data!$A$2:$A$301,0)) -> 38400 | K14: =INDEX(Sales_Data!$M$2:$M$301,MATCH($B14,Sales_Data!$A$2:$A$301,0)) -> 18400
A15: 12 | B15: TXN-1200 | C15: =INDEX(Sales_Data!$B$2:$B$301,MATCH($B15,Sales_Data!$A$2:$A$301,0)) -> 46161 | D15: =INDEX(Sales_Data!$C$2:$C$301,MATCH($B15,Sales_Data!$A$2:$A$301,0)) -> North | E15: =INDEX(Sales_Data!$D$2:$D$301,MATCH($B15,Sales_Data!$A$2:$A$301,0)) -> Tom Becker | F15: =INDEX(Sales_Data!$E$2:$E$301,MATCH($B15,Sales_Data!$A$2:$A$301,0)) -> Lumen Telecom | G15: =INDEX(Sales_Data!$F$2:$F$301,MATCH($B15,Sales_Data!$A$2:$A$301,0)) -> Business Laptop L5 | H15: =INDEX(Sales_Data!$H$2:$H$301,MATCH($B15,Sales_Data!$A$2:$A$301,0)) -> 25 | I15: =INDEX(Sales_Data!$J$2:$J$301,MATCH($B15,Sales_Data!$A$2:$A$301,0)) -> 0 | J15: =INDEX(Sales_Data!$L$2:$L$301,MATCH($B15,Sales_Data!$A$2:$A$301,0)) -> 36250 | K15: =INDEX(Sales_Data!$M$2:$M$301,MATCH($B15,Sales_Data!$A$2:$A$301,0)) -> 10000
... A18: 15 | B18: TXN-1170 | C18: =INDEX(Sales_Data!$B$2:$B$301,MATCH($B18,Sales_Data!$A$2:$A$301,0)) -> 46136 | D18: =INDEX(Sales_Data!$C$2:$C$301,MATCH($B18,Sales_Data!$A$2:$A$301,0)) -> North | E18: =INDEX(Sales_Data!$D$2:$D$301,MATCH($B18,Sales_Data!$A$2:$A$301,0)) -> Aisha Khan | F18: =INDEX(Sales_Data!$E$2:$E$301,MATCH($B18,Sales_Data!$A$2:$A$301,0)) -> Cobalt Systems | G18: =INDEX(Sales_Data!$F$2:$F$301,MATCH($B18,Sales_Data!$A$2:$A$301,0)) -> Onboarding Package | H18: =INDEX(Sales_Data!$H$2:$H$301,MATCH($B18,Sales_Data!$A$2:$A$301,0)) -> 20 | I18: =INDEX(Sales_Data!$J$2:$J$301,MATCH($B18,Sales_Data!$A$2:$A$301,0)) -> 0 | J18: =INDEX(Sales_Data!$L$2:$L$301,MATCH($B18,Sales_Data!$A$2:$A$301,0)) -> 36000 | K18: =INDEX(Sales_Data!$M$2:$M$301,MATCH($B18,Sales_Data!$A$2:$A$301,0)) -> 16000

Sheet High_Value
A1: High-Value Transactions (Revenue >= $32,400) - 32 transactions
A3: Rank | B3: Transaction ID | C3: Date | D3: Region | E3: Salesperson | F3: Customer | G3: Product | H3: Quantity | I3: Discount % | J3: Revenue ($) | K3: Profit ($)
A4: 1 | B4: TXN-1156 | C4: =INDEX(Sales_Data!$B$2:$B$301,MATCH($B4,Sales_Data!$A$2:$A$301,0)) -> 46117 | D4: =INDEX(Sales_Data!$C$2:$C$301,MATCH($B4,Sales_Data!$A$2:$A$301,0)) -> South | E4: =INDEX(Sales_Data!$D$2:$D$301,MATCH($B4,Sales_Data!$A$2:$A$301,0)) -> Priya Nair | F4: =INDEX(Sales_Data!$E$2:$E$301,MATCH($B4,Sales_Data!$A$2:$A$301,0)) -> Juniper Foods | G4: =INDEX(Sales_Data!$F$2:$F$301,MATCH($B4,Sales_Data!$A$2:$A$301,0)) -> Enterprise CRM Suite | H4: =INDEX(Sales_Data!$H$2:$H$301,MATCH($B4,Sales_Data!$A$2:$A$301,0)) -> 4 | I4: =INDEX(Sales_Data!$J$2:$J$301,MATCH($B4,Sales_Data!$A$2:$A$301,0)) -> 0 | J4: =INDEX(Sales_Data!$L$2:$L$301,MATCH($B4,Sales_Data!$A$2:$A$301,0)) -> 48000 | K4: =INDEX(Sales_Data!$M$2:$M$301,MATCH($B4,Sales_Data!$A$2:$A$301,0)) -> 28000
A5: 2 | B5: TXN-1227 | C5: =INDEX(Sales_Data!$B$2:$B$301,MATCH($B5,Sales_Data!$A$2:$A$301,0)) -> 46191 | D5: =INDEX(Sales_Data!$C$2:$C$301,MATCH($B5,Sales_Data!$A$2:$A$301,0)) -> North | E5: =INDEX(Sales_Data!$D$2:$D$301,MATCH($B5,Sales_Data!$A$2:$A$301,0)) -> Aisha Khan | F5: =INDEX(Sales_Data!$E$2:$E$301,MATCH($B5,Sales_Data!$A$2:$A$301,0)) -> BlueWave Ltd | G5: =INDEX(Sales_Data!$F$2:$F$301,MATCH($B5,Sales_Data!$A$2:$A$301,0)) -> Onboarding Package | H5: =INDEX(Sales_Data!$H$2:$H$301,MATCH($B5,Sales_Data!$A$2:$A$301,0)) -> 25 | I5: =INDEX(Sales_Data!$J$2:$J$301,MATCH($B5,Sales_Data!$A$2:$A$301,0)) -> 0 | J5: =INDEX(Sales_Data!$L$2:$L$301,MATCH($B5,Sales_Data!$A$2:$A$301,0)) -> 45000 | K5: =INDEX(Sales_Data!$M$2:$M$301,MATCH($B5,Sales_Data!$A$2:$A$301,0)) -> 20000
A6: 3 | B6: TXN-1204 | C6: =INDEX(Sales_Data!$B$2:$B$301,MATCH($B6,Sales_Data!$A$2:$A$301,0)) -> 46164 | D6: =INDEX(Sales_Data!$C$2:$C$301,MATCH($B6,Sales_Data!$A$2:$A$301,0)) -> North | E6: =INDEX(Sales_Data!$D$2:$D$301,MATCH($B6,Sales_Data!$A$2:$A$301,0)) -> Aisha Khan | F6: =INDEX(Sales_Data!$E$2:$E$301,MATCH($B6,Sales_Data!$A$2:$A$301,0)) -> Lumen Telecom | G6: =INDEX(Sales_Data!$F$2:$F$301,MATCH($B6,Sales_Data!$A$2:$A$301,0)) -> Enterprise CRM Suite | H6: =INDEX(Sales_Data!$H$2:$H$301,MATCH($B6,Sales_Data!$A$2:$A$301,0)) -> 4 | I6: =INDEX(Sales_Data!$J$2:$J$301,MATCH($B6,Sales_Data!$A$2:$A$301,0)) -> 0.1 | J6: =INDEX(Sales_Data!$L$2:$L$301,MATCH($B6,Sales_Data!$A$2:$A$301,0)) -> 43200 | K6: =INDEX(Sales_Data!$M$2:$M$301,MATCH($B6,Sales_Data!$A$2:$A$301,0)) -> 23200
A7: 4 | B7: TXN-1119 | C7: =INDEX(Sales_Data!$B$2:$B$301,MATCH($B7,Sales_Data!$A$2:$A$301,0)) -> 46077 | D7: =INDEX(Sales_Data!$C$2:$C$301,MATCH($B7,Sales_Data!$A$2:$A$301,0)) -> West | E7: =INDEX(Sales_Data!$D$2:$D$301,MATCH($B7,Sales_Data!$A$2:$A$301,0)) -> Sofia Rossi | F7: =INDEX(Sales_Data!$E$2:$E$301,MATCH($B7,Sales_Data!$A$2:$A$301,0)) -> Granite Bank | G7: =INDEX(Sales_Data!$F$2:$F$301,MATCH($B7,Sales_Data!$A$2:$A$301,0)) -> Enterprise CRM Suite | H7: =INDEX(Sales_Data!$H$2:$H$301,MATCH($B7,Sales_Data!$A$2:$A$301,0)) -> 4 | I7: =INDEX(Sales_Data!$J$2:$J$301,MATCH($B7,Sales_Data!$A$2:$A$301,0)) -> 0.1 | J7: =INDEX(Sales_Data!$L$2:$L$301,MATCH($B7,Sales_Data!$A$2:$A$301,0)) -> 43200 | K7: =INDEX(Sales_Data!$M$2:$M$301,MATCH($B7,Sales_Data!$A$2:$A$301,0)) -> 23200
A8: 5 | B8: TXN-1107 | C8: =INDEX(Sales_Data!$B$2:$B$301,MATCH($B8,Sales_Data!$A$2:$A$301,0)) -> 46059 | D8: =INDEX(Sales_Data!$C$2:$C$301,MATCH($B8,Sales_Data!$A$2:$A$301,0)) -> North | E8: =INDEX(Sales_Data!$D$2:$D$301,MATCH($B8,Sales_Data!$A$2:$A$301,0)) -> Tom Becker | F8: =INDEX(Sales_Data!$E$2:$E$301,MATCH($B8,Sales_Data!$A$2:$A$301,0)) -> Cobalt Systems | G8: =INDEX(Sales_Data!$F$2:$F$301,MATCH($B8,Sales_Data!$A$2:$A$301,0)) -> Onboarding Package | H8: =INDEX(Sales_Data!$H$2:$H$301,MATCH($B8,Sales_Data!$A$2:$A$301,0)) -> 25 | I8: =INDEX(Sales_Data!$J$2:$J$301,MATCH($B8,Sales_Data!$A$2:$A$301,0)) -> 0.05 | J8: =INDEX(Sales_Data!$L$2:$L$301,MATCH($B8,Sales_Data!$A$2:$A$301,0)) -> 42750 | K8: =INDEX(Sales_Data!$M$2:$M$301,MATCH($B8,Sales_Data!$A$2:$A$301,0)) -> 17750
A9: 6 | B9: TXN-1081 | C9: =INDEX(Sales_Data!$B$2:$B$301,MATCH($B9,Sales_Data!$A$2:$A$301,0)) -> 46029 | D9: =INDEX(Sales_Data!$C$2:$C$301,MATCH($B9,Sales_Data!$A$2:$A$301,0)) -> East | E9: =INDEX(Sales_Data!$D$2:$D$301,MATCH($B9,Sales_Data!$A$2:$A$301,0)) -> Marcus Hill | F9: =INDEX(Sales_Data!$E$2:$E$301,MATCH($B9,Sales_Data!$A$2:$A$301,0)) -> Cobalt Systems | G9: =INDEX(Sales_Data!$F$2:$F$301,MATCH($B9,Sales_Data!$A$2:$A$301,0)) -> Onboarding Package | H9: =INDEX(Sales_Data!$H$2:$H$301,MATCH($B9,Sales_Data!$A$2:$A$301,0)) -> 25 | I9: =INDEX(Sales_Data!$J$2:$J$301,MATCH($B9,Sales_Data!$A$2:$A$301,0)) -> 0.05 | J9: =INDEX(Sales_Data!$L$2:$L$301,MATCH($B9,Sales_Data!$A$2:$A$301,0)) -> 42750 | K9: =INDEX(Sales_Data!$M$2:$M$301,MATCH($B9,Sales_Data!$A$2:$A$301,0)) -> 17750
A10: 7 | B10: TXN-1124 | C10: =INDEX(Sales_Data!$B$2:$B$301,MATCH($B10,Sales_Data!$A$2:$A$301,0)) -> 46080 | D10: =INDEX(Sales_Data!$C$2:$C$301,MATCH($B10,Sales_Data!$A$2:$A$301,0)) -> West | E10: =INDEX(Sales_Data!$D$2:$D$301,MATCH($B10,Sales_Data!$A$2:$A$301,0)) -> Daniel Cho | F10: =INDEX(Sales_Data!$E$2:$E$301,MATCH($B10,Sales_Data!$A$2:$A$301,0)) -> Lumen Telecom | G10: =INDEX(Sales_Data!$F$2:$F$301,MATCH($B10,Sales_Data!$A$2:$A$301,0)) -> Enterprise CRM Suite | H10: =INDEX(Sales_Data!$H$2:$H$301,MATCH($B10,Sales_Data!$A$2:$A$301,0)) -> 4 | I10: =INDEX(Sales_Data!$J$2:$J$301,MATCH($B10,Sales_Data!$A$2:$A$301,0)) -> 0.15 | J10: =INDEX(Sales_Data!$L$2:$L$301,MATCH($B10,Sales_Data!$A$2:$A$301,0)) -> 40800 | K10: =INDEX(Sales_Data!$M$2:$M$301,MATCH($B10,Sales_Data!$A$2:$A$301,0)) -> 20800
A11: 8 | B11: TXN-1222 | C11: =INDEX(Sales_Data!$B$2:$B$301,MATCH($B11,Sales_Data!$A$2:$A$301,0)) -> 46186 | D11: =INDEX(Sales_Data!$C$2:$C$301,MATCH($B11,Sales_Data!$A$2:$A$301,0)) -> North | E11: =INDEX(Sales_Data!$D$2:$D$301,MATCH($B11,Sales_Data!$A$2:$A$301,0)) -> Aisha Khan | F11: =INDEX(Sales_Data!$E$2:$E$301,MATCH($B11,Sales_Data!$A$2:$A$301,0)) -> Keystone Edu | G11: =INDEX(Sales_Data!$F$2:$F$301,MATCH($B11,Sales_Data!$A$2:$A$301,0)) -> Server Rack X900 | H11: =INDEX(Sales_Data!$H$2:$H$301,MATCH($B11,Sales_Data!$A$2:$A$301,0)) -> 4 | I11: =INDEX(Sales_Data!$J$2:$J$301,MATCH($B11,Sales_Data!$A$2:$A$301,0)) -> 0 | J11: =INDEX(Sales_Data!$L$2:$L$301,MATCH($B11,Sales_Data!$A$2:$A$301,0)) -> 39200 | K11: =INDEX(Sales_Data!$M$2:$M$301,MATCH($B11,Sales_Data!$A$2:$A$301,0)) -> 10400
A12: 9 | B12: TXN-1214 | C12: =INDEX(Sales_Data!$B$2:$B$301,MATCH($B12,Sales_Data!$A$2:$A$301,0)) -> 46173 | D12: =INDEX(Sales_Data!$C$2:$C$301,MATCH($B12,Sales_Data!$A$2:$A$301,0)) -> East | E12: =INDEX(Sales_Data!$D$2:$D$301,MATCH($B12,Sales_Data!$A$2:$A$301,0)) -> Marcus Hill | F12: =INDEX(Sales_Data!$E$2:$E$301,MATCH($B12,Sales_Data!$A$2:$A$301,0)) -> Granite Bank | G12: =INDEX(Sales_Data!$F$2:$F$301,MATCH($B12,Sales_Data!$A$2:$A$301,0)) -> Server Rack X900 | H12: =INDEX(Sales_Data!$H$2:$H$301,MATCH($B12,Sales_Data!$A$2:$A$301,0)) -> 4 | I12: =INDEX(Sales_Data!$J$2:$J$301,MATCH($B12,Sales_Data!$A$2:$A$301,0)) -> 0 | J12: =INDEX(Sales_Data!$L$2:$L$301,MATCH($B12,Sales_Data!$A$2:$A$301,0)) -> 39200 | K12: =INDEX(Sales_Data!$M$2:$M$301,MATCH($B12,Sales_Data!$A$2:$A$301,0)) -> 10400
A13: 10 | B13: TXN-1019 | C13: =INDEX(Sales_Data!$B$2:$B$301,MATCH($B13,Sales_Data!$A$2:$A$301,0)) -> 45961 | D13: =INDEX(Sales_Data!$C$2:$C$301,MATCH($B13,Sales_Data!$A$2:$A$301,0)) -> West | E13: =INDEX(Sales_Data!$D$2:$D$301,MATCH($B13,Sales_Data!$A$2:$A$301,0)) -> Sofia Rossi | F13: =INDEX(Sales_Data!$E$2:$E$301,MATCH($B13,Sales_Data!$A$2:$A$301,0)) -> Granite Bank | G13: =INDEX(Sales_Data!$F$2:$F$301,MATCH($B13,Sales_Data!$A$2:$A$301,0)) -> Server Rack X900 | H13: =INDEX(Sales_Data!$H$2:$H$301,MATCH($B13,Sales_Data!$A$2:$A$301,0)) -> 4 | I13: =INDEX(Sales_Data!$J$2:$J$301,MATCH($B13,Sales_Data!$A$2:$A$301,0)) -> 0 | J13: =INDEX(Sales_Data!$L$2:$L$301,MATCH($B13,Sales_Data!$A$2:$A$301,0)) -> 39200 | K13: =INDEX(Sales_Data!$M$2:$M$301,MATCH($B13,Sales_Data!$A$2:$A$301,0)) -> 10400
A14: 11 | B14: TXN-1229 | C14: =INDEX(Sales_Data!$B$2:$B$301,MATCH($B14,Sales_Data!$A$2:$A$301,0)) -> 46193 | D14: =INDEX(Sales_Data!$C$2:$C$301,MATCH($B14,Sales_Data!$A$2:$A$301,0)) -> East | E14: =INDEX(Sales_Data!$D$2:$D$301,MATCH($B14,Sales_Data!$A$2:$A$301,0)) -> Marcus Hill | F14: =INDEX(Sales_Data!$E$2:$E$301,MATCH($B14,Sales_Data!$A$2:$A$301,0)) -> Ionic Energy | G14: =INDEX(Sales_Data!$F$2:$F$301,MATCH($B14,Sales_Data!$A$2:$A$301,0)) -> Enterprise CRM Suite | H14: =INDEX(Sales_Data!$H$2:$H$301,MATCH($B14,Sales_Data!$A$2:$A$301,0)) -> 4 | I14: =INDEX(Sales_Data!$J$2:$J$301,MATCH($B14,Sales_Data!$A$2:$A$301,0)) -> 0.2 | J14: =INDEX(Sales_Data!$L$2:$L$301,MATCH($B14,Sales_Data!$A$2:$A$301,0)) -> 38400 | K14: =INDEX(Sales_Data!$M$2:$M$301,MATCH($B14,Sales_Data!$A$2:$A$301,0)) -> 18400
A15: 12 | B15: TXN-1200 | C15: =INDEX(Sales_Data!$B$2:$B$301,MATCH($B15,Sales_Data!$A$2:$A$301,0)) -> 46161 | D15: =INDEX(Sales_Data!$C$2:$C$301,MATCH($B15,Sales_Data!$A$2:$A$301,0)) -> North | E15: =INDEX(Sales_Data!$D$2:$D$301,MATCH($B15,Sales_Data!$A$2:$A$301,0)) -> Tom Becker | F15: =INDEX(Sales_Data!$E$2:$E$301,MATCH($B15,Sales_Data!$A$2:$A$301,0)) -> Lumen Telecom | G15: =INDEX(Sales_Data!$F$2:$F$301,MATCH($B15,Sales_Data!$A$2:$A$301,0)) -> Business Laptop L5 | H15: =INDEX(Sales_Data!$H$2:$H$301,MATCH($B15,Sales_Data!$A$2:$A$301,0)) -> 25 | I15: =INDEX(Sales_Data!$J$2:$J$301,MATCH($B15,Sales_Data!$A$2:$A$301,0)) -> 0 | J15: =INDEX(Sales_Data!$L$2:$L$301,MATCH($B15,Sales_Data!$A$2:$A$301,0)) -> 36250 | K15: =INDEX(Sales_Data!$M$2:$M$301,MATCH($B15,Sales_Data!$A$2:$A$301,0)) -> 10000
... A35: 32 | B35: TXN-1114 | C35: =INDEX(Sales_Data!$B$2:$B$301,MATCH($B35,Sales_Data!$A$2:$A$301,0)) -> 46071 | D35: =INDEX(Sales_Data!$C$2:$C$301,MATCH($B35,Sales_Data!$A$2:$A$301,0)) -> West | E35: =INDEX(Sales_Data!$D$2:$D$301,MATCH($B35,Sales_Data!$A$2:$A$301,0)) -> Sofia Rossi | F35: =INDEX(Sales_Data!$E$2:$E$301,MATCH($B35,Sales_Data!$A$2:$A$301,0)) -> BlueWave Ltd | G35: =INDEX(Sales_Data!$F$2:$F$301,MATCH($B35,Sales_Data!$A$2:$A$301,0)) -> Enterprise CRM Suite | H35: =INDEX(Sales_Data!$H$2:$H$301,MATCH($B35,Sales_Data!$A$2:$A$301,0)) -> 3 | I35: =INDEX(Sales_Data!$J$2:$J$301,MATCH($B35,Sales_Data!$A$2:$A$301,0)) -> 0.1 | J35: =INDEX(Sales_Data!$L$2:$L$301,MATCH($B35,Sales_Data!$A$2:$A$301,0)) -> 32400 | K35: =INDEX(Sales_Data!$M$2:$M$301,MATCH($B35,Sales_Data!$A$2:$A$301,0)) -> 17400

Sheet Underperformers
A1: Underperforming Products (sorted by revenue, lowest first)
A3: Product | B3: Category | C3: Units Sold | D3: Revenue ($) | E3: Profit ($) | F3: Margin % | G3: Return Rate | H3: Status
A4: Legacy Fax Gateway | B4: =INDEX(Product_Summary!$B$7:$B$18,MATCH($A4,Product_Summary!$A$7:$A$18,0)) -> Hardware | C4: =INDEX(Product_Summary!$D$7:$D$18,MATCH($A4,Product_Summary!$A$7:$A$18,0)) -> 22 | D4: =INDEX(Product_Summary!$E$7:$E$18,MATCH($A4,Product_Summary!$A$7:$A$18,0)) -> 7942.5 | E4: =INDEX(Product_Summary!$F$7:$F$18,MATCH($A4,Product_Summary!$A$7:$A$18,0)) -> -1077.5 | F4: =INDEX(Product_Summary!$G$7:$G$18,MATCH($A4,Product_Summary!$A$7:$A$18,0)) -> -0.13566257 | G4: =INDEX(Product_Summary!$H$7:$H$18,MATCH($A4,Product_Summary!$A$7:$A$18,0)) -> 0 | H4: =INDEX(Product_Summary!$J$7:$J$18,MATCH($A4,Product_Summary!$A$7:$A$18,0)) -> Underperforming
A5: Basic Training Kit | B5: =INDEX(Product_Summary!$B$7:$B$18,MATCH($A5,Product_Summary!$A$7:$A$18,0)) -> Services | C5: =INDEX(Product_Summary!$D$7:$D$18,MATCH($A5,Product_Summary!$A$7:$A$18,0)) -> 61 | D5: =INDEX(Product_Summary!$E$7:$E$18,MATCH($A5,Product_Summary!$A$7:$A$18,0)) -> 26970 | E5: =INDEX(Product_Summary!$F$7:$F$18,MATCH($A5,Product_Summary!$A$7:$A$18,0)) -> -4750 | F5: =INDEX(Product_Summary!$G$7:$G$18,MATCH($A5,Product_Summary!$A$7:$A$18,0)) -> -0.17612162 | G5: =INDEX(Product_Summary!$H$7:$H$18,MATCH($A5,Product_Summary!$A$7:$A$18,0)) -> 0 | H5: =INDEX(Product_Summary!$J$7:$J$18,MATCH($A5,Product_Summary!$A$7:$A$18,0)) -> Underperforming
A6: Smart Display 55in | B6: =INDEX(Product_Summary!$B$7:$B$18,MATCH($A6,Product_Summary!$A$7:$A$18,0)) -> Hardware | C6: =INDEX(Product_Summary!$D$7:$D$18,MATCH($A6,Product_Summary!$A$7:$A$18,0)) -> 24 | D6: =INDEX(Product_Summary!$E$7:$E$18,MATCH($A6,Product_Summary!$A$7:$A$18,0)) -> 33155 | E6: =INDEX(Product_Summary!$F$7:$F$18,MATCH($A6,Product_Summary!$A$7:$A$18,0)) -> -6445 | F6: =INDEX(Product_Summary!$G$7:$G$18,MATCH($A6,Product_Summary!$A$7:$A$18,0)) -> -0.19438999 | G6: =INDEX(Product_Summary!$H$7:$H$18,MATCH($A6,Product_Summary!$A$7:$A$18,0)) -> 0 | H6: =INDEX(Product_Summary!$J$7:$J$18,MATCH($A6,Product_Summary!$A$7:$A$18,0)) -> Underperforming
A7: Wireless Router W2 | B7: =INDEX(Product_Summary!$B$7:$B$18,MATCH($A7,Product_Summary!$A$7:$A$18,0)) -> Hardware | C7: =INDEX(Product_Summary!$D$7:$D$18,MATCH($A7,Product_Summary!$A$7:$A$18,0)) -> 706 | D7: =INDEX(Product_Summary!$E$7:$E$18,MATCH($A7,Product_Summary!$A$7:$A$18,0)) -> 206512 | E7: =INDEX(Product_Summary!$F$7:$F$18,MATCH($A7,Product_Summary!$A$7:$A$18,0)) -> 37072 | F7: =INDEX(Product_Summary!$G$7:$G$18,MATCH($A7,Product_Summary!$A$7:$A$18,0)) -> 0.17951499 | G7: =INDEX(Product_Summary!$H$7:$H$18,MATCH($A7,Product_Summary!$A$7:$A$18,0)) -> 0.016393443 | H7: =INDEX(Product_Summary!$J$7:$J$18,MATCH($A7,Product_Summary!$A$7:$A$18,0)) -> Underperforming
